tablestore_for_agent_memory/base/__init__.py
tablestore_for_agent_memory/base/base_knowledge_store.py
tablestore_for_agent_memory/base/base_memory_store.py
tablestore_for_agent_memory/base/common.py
tablestore_for_agent_memory/base/filter.py
tablestore_for_agent_memory/knowledge/__init__.py
tablestore_for_agent_memory/knowledge/async_knowledge_store.py
tablestore_for_agent_memory/knowledge/knowledge_store.py
tablestore_for_agent_memory/memory/__init__.py
tablestore_for_agent_memory/memory/async_memory_store.py
tablestore_for_agent_memory/memory/memory_store.py
tablestore_for_agent_memory/util/__init__.py
tablestore_for_agent_memory/util/tablestore_helper.py
tablestore_for_agent_memory-1.1.2.dist-info/METADATA
tablestore_for_agent_memory-1.1.2.dist-info/WHEEL
tablestore_for_agent_memory-1.1.2.dist-info/licenses/LICENSE
tablestore_for_agent_memory-1.1.2.dist-info/RECORD
