Metadata-Version: 2.4
Name: tablestore-for-agent-memory
Version: 1.1.2
Summary: Tablestore for Agent Memory in AI Agent.
License: Apache-2.0
License-File: LICENSE
Author: xunjian.sl
Author-email: xunjian.sl@alibaba-inc.com
Requires-Python: >=3.9,<4.0
Classifier: License :: OSI Approved :: Apache Software License
Classifier: Programming Language :: Python :: 3
Classifier: Programming Language :: Python :: 3.9
Classifier: Programming Language :: Python :: 3.10
Classifier: Programming Language :: Python :: 3.11
Classifier: Programming Language :: Python :: 3.12
Classifier: Programming Language :: Python :: 3.13
Classifier: Programming Language :: Python :: 3.14
Requires-Dist: pydantic (>=2.10.6,<3.0.0)
Requires-Dist: tablestore (>=6.3.8,<7.0.0)
Project-URL: Homepage, https://www.aliyun.com/product/ots
